Lego/__init__.py
Lego/CLASSES___Lego.py
Lego-0.1.3.dist-info/DESCRIPTION.rst
Lego-0.1.3.dist-info/METADATA
Lego-0.1.3.dist-info/metadata.json
Lego-0.1.3.dist-info/RECORD
Lego-0.1.3.dist-info/top_level.txt
Lego-0.1.3.dist-info/WHEEL
