Metadata-Version: 2.0
Name: Lego
Version: 0.1.3
Summary: Lego
Home-page: https://github.com/MBALearnsToCode/Lego
Author: Vinh Luong (a.k.a. MBALearnsToCode)
Author-email: MBALearnsToCode@UChicago.edu
License: MIT License
Keywords: lego
Platform: UNKNOWN
